CHANGELOG.md
pydantic_openapi_schema/__init__.py
pydantic_openapi_schema/py.typed
pydantic_openapi_schema/utils/__init__.py
pydantic_openapi_schema/utils/utils.py
pydantic_openapi_schema/v3_1_0/__init__.py
pydantic_openapi_schema/v3_1_0/callback.py
pydantic_openapi_schema/v3_1_0/components.py
pydantic_openapi_schema/v3_1_0/contact.py
pydantic_openapi_schema/v3_1_0/discriminator.py
pydantic_openapi_schema/v3_1_0/encoding.py
pydantic_openapi_schema/v3_1_0/example.py
pydantic_openapi_schema/v3_1_0/external_documentation.py
pydantic_openapi_schema/v3_1_0/header.py
pydantic_openapi_schema/v3_1_0/info.py
pydantic_openapi_schema/v3_1_0/license.py
pydantic_openapi_schema/v3_1_0/link.py
pydantic_openapi_schema/v3_1_0/media_type.py
pydantic_openapi_schema/v3_1_0/oauth_flow.py
pydantic_openapi_schema/v3_1_0/oauth_flows.py
pydantic_openapi_schema/v3_1_0/open_api.py
pydantic_openapi_schema/v3_1_0/operation.py
pydantic_openapi_schema/v3_1_0/parameter.py
pydantic_openapi_schema/v3_1_0/path_item.py
pydantic_openapi_schema/v3_1_0/paths.py
pydantic_openapi_schema/v3_1_0/reference.py
pydantic_openapi_schema/v3_1_0/request_body.py
pydantic_openapi_schema/v3_1_0/response.py
pydantic_openapi_schema/v3_1_0/responses.py
pydantic_openapi_schema/v3_1_0/schema.py
pydantic_openapi_schema/v3_1_0/security_requirement.py
pydantic_openapi_schema/v3_1_0/security_scheme.py
pydantic_openapi_schema/v3_1_0/server.py
pydantic_openapi_schema/v3_1_0/server_variable.py
pydantic_openapi_schema/v3_1_0/tag.py
pydantic_openapi_schema/v3_1_0/xml.py
pydantic_openapi_schema-1.5.1.dist-info/WHEEL
pydantic_openapi_schema-1.5.1.dist-info/LICENSE
pydantic_openapi_schema-1.5.1.dist-info/METADATA
pydantic_openapi_schema-1.5.1.dist-info/RECORD
