Metadata-Version: 2.1
Name: pydantic-openapi-schema
Version: 1.5.1
Summary: OpenAPI Schema using pydantic. Forked for Starlite-API from 'openapi-schema-pydantic'.
License: MIT
Keywords: openAPI,open-api,starlite,pydantic,schema
Author: Na'aman Hirschfeld
Author-email: nhirschfeld@gmail.com
Maintainer: Na'aman Hirschfeld
Maintainer-email: nhirschfeld@gmail.com
Requires-Python: >=3.8
Classifier: Development Status :: 5 - Production/Stable
Classifier: Environment :: Web Environment
Classifier: License :: OSI Approved :: MIT License
Classifier: Natural Language :: English
Classifier: Operating System :: OS Independent
Classifier: Programming Language :: Python
Classifier: Programming Language :: Python :: 3
Classifier: Programming Language :: Python :: 3.8
Classifier: Programming Language :: Python :: 3.9
Classifier: Programming Language :: Python :: 3.10
Classifier: Programming Language :: Python :: 3.11
Classifier: Programming Language :: Python :: 3.10
Classifier: Programming Language :: Python :: 3.11
Classifier: Programming Language :: Python :: 3.8
Classifier: Programming Language :: Python :: 3.9
Classifier: Topic :: Internet :: WWW/HTTP
Classifier: Topic :: Software Development
Classifier: Topic :: Software Development :: Libraries
Classifier: Typing :: Typed
Requires-Dist: email-validator
Requires-Dist: pydantic (>=1.10.0)
